cubicweb_i18nfield/__init__.py
cubicweb_i18nfield/__pkginfo__.py
cubicweb_i18nfield/entities.py
cubicweb_i18nfield/hooks.py
cubicweb_i18nfield/schema.py
cubicweb_i18nfield/uiprops.py
cubicweb_i18nfield/utils.py
cubicweb_i18nfield/views.py
cubicweb_i18nfield/data/cubes.i18nfield.css
cubicweb_i18nfield/i18n/de.po
cubicweb_i18nfield/i18n/en.po
cubicweb_i18nfield/i18n/es.po
cubicweb_i18nfield/i18n/fr.po
cubicweb_i18nfield/migration/0.1.1_Any.py
cubicweb_i18nfield/migration/postcreate.py
cubicweb_i18nfield-1.0.1.dist-info/METADATA
cubicweb_i18nfield-1.0.1.dist-info/WHEEL
cubicweb_i18nfield-1.0.1.dist-info/entry_points.txt
cubicweb_i18nfield-1.0.1.dist-info/top_level.txt
cubicweb_i18nfield-1.0.1.dist-info/RECORD
