Metadata-Version: 2.4
Name: cubicweb-i18nfield
Version: 1.0.1
Summary: Provides a way to translate entity fields individually.
Home-page: http://www.cubicweb.org/project/cubicweb-i18nfield
Author: Florent Cayré (Villejuif, FRANCE)
Author-email: Florent Cayré <florent.cayre@gmail.com>
License: LGPL
Classifier: Environment :: Web Environment
Classifier: Framework :: CubicWeb
Classifier: Programming Language :: Python
Classifier: Programming Language :: Python :: 3 :: Only
Classifier: Programming Language :: JavaScript
Requires-Dist: cubicweb<5.0.0,>=4.0.0
Requires-Dist: cubicweb-web<2.0.0,>=1.4.0
Requires-Dist: cubicweb-card<3.0.0,>=2.0.0
Dynamic: author
Dynamic: author-email
Dynamic: classifier
Dynamic: description
Dynamic: home-page
Dynamic: license
Dynamic: requires-dist
Dynamic: summary
